persistmq/__init__.py
persistmq/client.py
persistmq-0.1.4.dist-info/METADATA
persistmq-0.1.4.dist-info/WHEEL
persistmq-0.1.4.dist-info/licenses/LICENSE
persistmq-0.1.4.dist-info/RECORD
