Metadata-Version: 2.4
Name: persistmq
Version: 0.1.4
Summary: A robust mqtt library with message caching
Project-URL: Homepage, https://github.com/DaqOpen/persistmq
Project-URL: Issues, https://github.com/DaqOpen/persistmq/issues
Author-email: Michael Oberhofer <info@pqopen.com>
License-File: LICENSE
Classifier: License :: OSI Approved :: MIT License
Classifier: Operating System :: OS Independent
Classifier: Programming Language :: Python :: 3
Requires-Python: >=3.11
Requires-Dist: cbor2
Requires-Dist: paho-mqtt
